{
    "@odata.context": "/redfish/v1/$metadata#HpePowerMeter.HpePowerMeter",
    "@odata.etag": "W/\"747580691\"",
    "@odata.id": "/redfish/v1/Chassis/1/Power/FastPowerMeter",
    "@odata.type": "#HpePowerMeter.v2_1_0.HpePowerMeter",
    "Id": "FastPowerMeter",
    "Average": 967,
    "Maximum": 971,
    "Minimum": 966,
    "Name": "PowerMeter",
    "PowerDetail": [
        {
            "AmbTemp": 16,
            "Average": 968,
            "Cap": 0,
            "CpuAvgFreq": 0,
            "CpuCapLim": 0,
            "CpuMax": 0,
            "CpuPwrSavLim": 100,
            "CpuUtil": 0,
            "CpuWatts": 168,
            "DimmWatts": 36,
            "FanWatts": 46,
            "GpuWatts": 0,
            "Minimum": 968,
            "Peak": 970,
            "PrMode": "dyn",
            "PunCap": false,
            "Time": "2025-07-16T23:07:00Z",
            "UnachCap": false
        },
        {
            "AmbTemp": 16,
            "Average": 967,
            "Cap": 0,
            "CpuAvgFreq": 0,
            "CpuCapLim": 0,
            "CpuMax": 0,
            "CpuPwrSavLim": 100,
            "CpuUtil": 0,
            "CpuWatts": 168,
            "DimmWatts": 36,
            "FanWatts": 46,
            "GpuWatts": 0,
            "Minimum": 967,
            "Peak": 969,
            "PrMode": "dyn",
            "PunCap": false,
            "Time": "2025-07-16T23:07:10Z",
            "UnachCap": false
        },
        {
            "AmbTemp": 16,
            "Average": 966,
            "Cap": 0,
            "CpuAvgFreq": 0,
            "CpuCapLim": 0,
            "CpuMax": 0,
            "CpuPwrSavLim": 100,
            "CpuUtil": 0,
            "CpuWatts": 163,
            "DimmWatts": 36,
            "FanWatts": 46,
            "GpuWatts": 0,
            "Minimum": 966,
            "Peak": 968,
            "PrMode": "dyn",
            "PunCap": false,
            "Time": "2025-07-16T23:07:20Z",
            "UnachCap": false
        },
        {
            "AmbTemp": 16,
            "Average": 968,
            "Cap": 0,
            "CpuAvgFreq": 0,
            "CpuCapLim": 0,
            "CpuMax": 0,
            "CpuPwrSavLim": 100,
            "CpuUtil": 0,
            "CpuWatts": 164,
            "DimmWatts": 36,
            "FanWatts": 46,
            "GpuWatts": 0,
            "Minimum": 968,
            "Peak": 968,
            "PrMode": "dyn",
            "PunCap": false,
            "Time": "2025-07-16T23:07:31Z",
            "UnachCap": false
        },
        {
            "AmbTemp": 16,
            "Average": 967,
            "Cap": 0,
            "CpuAvgFreq": 0,
            "CpuCapLim": 0,
            "CpuMax": 0,
            "CpuPwrSavLim": 100,
            "CpuUtil": 0,
            "CpuWatts": 169,
            "DimmWatts": 36,
            "FanWatts": 46,
            "GpuWatts": 0,
            "Minimum": 967,
            "Peak": 967,
            "PrMode": "dyn",
            "PunCap": false,
            "Time": "2025-07-16T23:07:41Z",
            "UnachCap": false
        },
        {
            "AmbTemp": 16,
            "Average": 969,
            "Cap": 0,
            "CpuAvgFreq": 0,
            "CpuCapLim": 0,
            "CpuMax": 0,
            "CpuPwrSavLim": 100,
            "CpuUtil": 0,
            "CpuWatts": 166,
            "DimmWatts": 36,
            "FanWatts": 46,
            "GpuWatts": 0,
            "Minimum": 969,
            "Peak": 967,
            "PrMode": "dyn",
            "PunCap": false,
            "Time": "2025-07-16T23:07:51Z",
            "UnachCap": false
        },
        {
            "AmbTemp": 16,
            "Average": 967,
            "Cap": 0,
            "CpuAvgFreq": 0,
            "CpuCapLim": 0,
            "CpuMax": 0,
            "CpuPwrSavLim": 100,
            "CpuUtil": 0,
            "CpuWatts": 161,
            "DimmWatts": 36,
            "FanWatts": 46,
            "GpuWatts": 0,
            "Minimum": 967,
            "Peak": 966,
            "PrMode": "dyn",
            "PunCap": false,
            "Time": "2025-07-16T23:08:02Z",
            "UnachCap": false
        },
        {
            "AmbTemp": 16,
            "Average": 967,
            "Cap": 0,
            "CpuAvgFreq": 0,
            "CpuCapLim": 0,
            "CpuMax": 0,
            "CpuPwrSavLim": 100,
            "CpuUtil": 0,
            "CpuWatts": 166,
            "DimmWatts": 36,
            "FanWatts": 46,
            "GpuWatts": 0,
            "Minimum": 967,
            "Peak": 969,
            "PrMode": "dyn",
            "PunCap": false,
            "Time": "2025-07-16T23:08:12Z",
            "UnachCap": false
        },
        {
            "AmbTemp": 16,
            "Average": 967,
            "Cap": 0,
            "CpuAvgFreq": 0,
            "CpuCapLim": 0,
            "CpuMax": 0,
            "CpuPwrSavLim": 100,
            "CpuUtil": 0,
            "CpuWatts": 168,
            "DimmWatts": 36,
            "FanWatts": 46,
            "GpuWatts": 0,
            "Minimum": 967,
            "Peak": 969,
            "PrMode": "dyn",
            "PunCap": false,
            "Time": "2025-07-16T23:08:23Z",
            "UnachCap": false
        },
        {
            "AmbTemp": 16,
            "Average": 967,
            "Cap": 0,
            "CpuAvgFreq": 0,
            "CpuCapLim": 0,
            "CpuMax": 0,
            "CpuPwrSavLim": 100,
            "CpuUtil": 0,
            "CpuWatts": 169,
            "DimmWatts": 36,
            "FanWatts": 46,
            "GpuWatts": 0,
            "Minimum": 967,
            "Peak": 969,
            "PrMode": "dyn",
            "PunCap": false,
            "Time": "2025-07-16T23:08:34Z",
            "UnachCap": false
        },
        {
            "AmbTemp": 16,
            "Average": 968,
            "Cap": 0,
            "CpuAvgFreq": 0,
            "CpuCapLim": 0,
            "CpuMax": 0,
            "CpuPwrSavLim": 100,
            "CpuUtil": 0,
            "CpuWatts": 167,
            "DimmWatts": 36,
            "FanWatts": 46,
            "GpuWatts": 0,
            "Minimum": 968,
            "Peak": 965,
            "PrMode": "dyn",
            "PunCap": false,
            "Time": "2025-07-16T23:08:44Z",
            "UnachCap": false
        },
        {
            "AmbTemp": 16,
            "Average": 968,
            "Cap": 0,
            "CpuAvgFreq": 0,
            "CpuCapLim": 0,
            "CpuMax": 0,
            "CpuPwrSavLim": 100,
            "CpuUtil": 0,
            "CpuWatts": 163,
            "DimmWatts": 36,
            "FanWatts": 46,
            "GpuWatts": 0,
            "Minimum": 968,
            "Peak": 969,
            "PrMode": "dyn",
            "PunCap": false,
            "Time": "2025-07-16T23:08:54Z",
            "UnachCap": false
        },
        {
            "AmbTemp": 16,
            "Average": 967,
            "Cap": 0,
            "CpuAvgFreq": 0,
            "CpuCapLim": 0,
            "CpuMax": 0,
            "CpuPwrSavLim": 100,
            "CpuUtil": 0,
            "CpuWatts": 167,
            "DimmWatts": 36,
            "FanWatts": 46,
            "GpuWatts": 0,
            "Minimum": 967,
            "Peak": 968,
            "PrMode": "dyn",
            "PunCap": false,
            "Time": "2025-07-16T23:09:05Z",
            "UnachCap": false
        },
        {
            "AmbTemp": 16,
            "Average": 966,
            "Cap": 0,
            "CpuAvgFreq": 0,
            "CpuCapLim": 0,
            "CpuMax": 0,
            "CpuPwrSavLim": 100,
            "CpuUtil": 0,
            "CpuWatts": 168,
            "DimmWatts": 36,
            "FanWatts": 46,
            "GpuWatts": 0,
            "Minimum": 966,
            "Peak": 968,
            "PrMode": "dyn",
            "PunCap": false,
            "Time": "2025-07-16T23:09:15Z",
            "UnachCap": false
        },
        {
            "AmbTemp": 16,
            "Average": 968,
            "Cap": 0,
            "CpuAvgFreq": 0,
            "CpuCapLim": 0,
            "CpuMax": 0,
            "CpuPwrSavLim": 100,
            "CpuUtil": 0,
            "CpuWatts": 169,
            "DimmWatts": 36,
            "FanWatts": 46,
            "GpuWatts": 0,
            "Minimum": 968,
            "Peak": 966,
            "PrMode": "dyn",
            "PunCap": false,
            "Time": "2025-07-16T23:09:25Z",
            "UnachCap": false
        },
        {
            "AmbTemp": 16,
            "Average": 967,
            "Cap": 0,
            "CpuAvgFreq": 0,
            "CpuCapLim": 0,
            "CpuMax": 0,
            "CpuPwrSavLim": 100,
            "CpuUtil": 0,
            "CpuWatts": 164,
            "DimmWatts": 36,
            "FanWatts": 46,
            "GpuWatts": 0,
            "Minimum": 967,
            "Peak": 970,
            "PrMode": "dyn",
            "PunCap": false,
            "Time": "2025-07-16T23:09:36Z",
            "UnachCap": false
        },
        {
            "AmbTemp": 16,
            "Average": 967,
            "Cap": 0,
            "CpuAvgFreq": 0,
            "CpuCapLim": 0,
            "CpuMax": 0,
            "CpuPwrSavLim": 100,
            "CpuUtil": 0,
            "CpuWatts": 165,
            "DimmWatts": 36,
            "FanWatts": 46,
            "GpuWatts": 0,
            "Minimum": 967,
            "Peak": 968,
            "PrMode": "dyn",
            "PunCap": false,
            "Time": "2025-07-16T23:09:46Z",
            "UnachCap": false
        },
        {
            "AmbTemp": 16,
            "Average": 968,
            "Cap": 0,
            "CpuAvgFreq": 0,
            "CpuCapLim": 0,
            "CpuMax": 0,
            "CpuPwrSavLim": 100,
            "CpuUtil": 0,
            "CpuWatts": 166,
            "DimmWatts": 36,
            "FanWatts": 46,
            "GpuWatts": 0,
            "Minimum": 968,
            "Peak": 969,
            "PrMode": "dyn",
            "PunCap": false,
            "Time": "2025-07-16T23:09:56Z",
            "UnachCap": false
        },
        {
            "AmbTemp": 16,
            "Average": 968,
            "Cap": 0,
            "CpuAvgFreq": 0,
            "CpuCapLim": 0,
            "CpuMax": 0,
            "CpuPwrSavLim": 100,
            "CpuUtil": 0,
            "CpuWatts": 169,
            "DimmWatts": 36,
            "FanWatts": 46,
            "GpuWatts": 0,
            "Minimum": 968,
            "Peak": 969,
            "PrMode": "dyn",
            "PunCap": false,
            "Time": "2025-07-16T23:10:07Z",
            "UnachCap": false
        },
        {
            "AmbTemp": 16,
            "Average": 966,
            "Cap": 0,
            "CpuAvgFreq": 0,
            "CpuCapLim": 0,
            "CpuMax": 0,
            "CpuPwrSavLim": 100,
            "CpuUtil": 0,
            "CpuWatts": 167,
            "DimmWatts": 36,
            "FanWatts": 46,
            "GpuWatts": 0,
            "Minimum": 966,
            "Peak": 965,
            "PrMode": "dyn",
            "PunCap": false,
            "Time": "2025-07-16T23:10:17Z",
            "UnachCap": false
        },
        {
            "AmbTemp": 16,
            "Average": 967,
            "Cap": 0,
            "CpuAvgFreq": 0,
            "CpuCapLim": 0,
            "CpuMax": 0,
            "CpuPwrSavLim": 100,
            "CpuUtil": 0,
            "CpuWatts": 164,
            "DimmWatts": 36,
            "FanWatts": 46,
            "GpuWatts": 0,
            "Minimum": 967,
            "Peak": 968,
            "PrMode": "dyn",
            "PunCap": false,
            "Time": "2025-07-16T23:10:28Z",
            "UnachCap": false
        },
        {
            "AmbTemp": 16,
            "Average": 966,
            "Cap": 0,
            "CpuAvgFreq": 0,
            "CpuCapLim": 0,
            "CpuMax": 0,
            "CpuPwrSavLim": 100,
            "CpuUtil": 0,
            "CpuWatts": 170,
            "DimmWatts": 36,
            "FanWatts": 46,
            "GpuWatts": 0,
            "Minimum": 966,
            "Peak": 967,
            "PrMode": "dyn",
            "PunCap": false,
            "Time": "2025-07-16T23:10:38Z",
            "UnachCap": false
        },
        {
            "AmbTemp": 16,
            "Average": 968,
            "Cap": 0,
            "CpuAvgFreq": 0,
            "CpuCapLim": 0,
            "CpuMax": 0,
            "CpuPwrSavLim": 100,
            "CpuUtil": 0,
            "CpuWatts": 167,
            "DimmWatts": 36,
            "FanWatts": 46,
            "GpuWatts": 0,
            "Minimum": 968,
            "Peak": 968,
            "PrMode": "dyn",
            "PunCap": false,
            "Time": "2025-07-16T23:10:49Z",
            "UnachCap": false
        },
        {
            "AmbTemp": 16,
            "Average": 967,
            "Cap": 0,
            "CpuAvgFreq": 0,
            "CpuCapLim": 0,
            "CpuMax": 0,
            "CpuPwrSavLim": 100,
            "CpuUtil": 0,
            "CpuWatts": 168,
            "DimmWatts": 36,
            "FanWatts": 46,
            "GpuWatts": 0,
            "Minimum": 967,
            "Peak": 969,
            "PrMode": "dyn",
            "PunCap": false,
            "Time": "2025-07-16T23:10:59Z",
            "UnachCap": false
        },
        {
            "AmbTemp": 16,
            "Average": 969,
            "Cap": 0,
            "CpuAvgFreq": 0,
            "CpuCapLim": 0,
            "CpuMax": 0,
            "CpuPwrSavLim": 100,
            "CpuUtil": 0,
            "CpuWatts": 167,
            "DimmWatts": 36,
            "FanWatts": 46,
            "GpuWatts": 0,
            "Minimum": 969,
            "Peak": 968,
            "PrMode": "dyn",
            "PunCap": false,
            "Time": "2025-07-16T23:11:09Z",
            "UnachCap": false
        },
        {
            "AmbTemp": 16,
            "Average": 967,
            "Cap": 0,
            "CpuAvgFreq": 0,
            "CpuCapLim": 0,
            "CpuMax": 0,
            "CpuPwrSavLim": 100,
            "CpuUtil": 0,
            "CpuWatts": 166,
            "DimmWatts": 36,
            "FanWatts": 46,
            "GpuWatts": 0,
            "Minimum": 967,
            "Peak": 969,
            "PrMode": "dyn",
            "PunCap": false,
            "Time": "2025-07-16T23:11:20Z",
            "UnachCap": false
        },
        {
            "AmbTemp": 16,
            "Average": 968,
            "Cap": 0,
            "CpuAvgFreq": 0,
            "CpuCapLim": 0,
            "CpuMax": 0,
            "CpuPwrSavLim": 100,
            "CpuUtil": 0,
            "CpuWatts": 168,
            "DimmWatts": 36,
            "FanWatts": 46,
            "GpuWatts": 0,
            "Minimum": 968,
            "Peak": 967,
            "PrMode": "dyn",
            "PunCap": false,
            "Time": "2025-07-16T23:11:30Z",
            "UnachCap": false
        },
        {
            "AmbTemp": 15,
            "Average": 969,
            "Cap": 0,
            "CpuAvgFreq": 0,
            "CpuCapLim": 0,
            "CpuMax": 0,
            "CpuPwrSavLim": 100,
            "CpuUtil": 0,
            "CpuWatts": 162,
            "DimmWatts": 36,
            "FanWatts": 46,
            "GpuWatts": 0,
            "Minimum": 969,
            "Peak": 969,
            "PrMode": "dyn",
            "PunCap": false,
            "Time": "2025-07-16T23:11:41Z",
            "UnachCap": false
        },
        {
            "AmbTemp": 15,
            "Average": 967,
            "Cap": 0,
            "CpuAvgFreq": 0,
            "CpuCapLim": 0,
            "CpuMax": 0,
            "CpuPwrSavLim": 100,
            "CpuUtil": 0,
            "CpuWatts": 168,
            "DimmWatts": 36,
            "FanWatts": 46,
            "GpuWatts": 0,
            "Minimum": 967,
            "Peak": 968,
            "PrMode": "dyn",
            "PunCap": false,
            "Time": "2025-07-16T23:11:51Z",
            "UnachCap": false
        },
        {
            "AmbTemp": 16,
            "Average": 968,
            "Cap": 0,
            "CpuAvgFreq": 0,
            "CpuCapLim": 0,
            "CpuMax": 0,
            "CpuPwrSavLim": 100,
            "CpuUtil": 0,
            "CpuWatts": 166,
            "DimmWatts": 36,
            "FanWatts": 46,
            "GpuWatts": 0,
            "Minimum": 968,
            "Peak": 968,
            "PrMode": "dyn",
            "PunCap": false,
            "Time": "2025-07-16T23:12:01Z",
            "UnachCap": false
        },
        {
            "AmbTemp": 16,
            "Average": 967,
            "Cap": 0,
            "CpuAvgFreq": 0,
            "CpuCapLim": 0,
            "CpuMax": 0,
            "CpuPwrSavLim": 100,
            "CpuUtil": 0,
            "CpuWatts": 167,
            "DimmWatts": 36,
            "FanWatts": 46,
            "GpuWatts": 0,
            "Minimum": 967,
            "Peak": 968,
            "PrMode": "dyn",
            "PunCap": false,
            "Time": "2025-07-16T23:12:11Z",
            "UnachCap": false
        },
        {
            "AmbTemp": 15,
            "Average": 967,
            "Cap": 0,
            "CpuAvgFreq": 0,
            "CpuCapLim": 0,
            "CpuMax": 0,
            "CpuPwrSavLim": 100,
            "CpuUtil": 0,
            "CpuWatts": 165,
            "DimmWatts": 36,
            "FanWatts": 46,
            "GpuWatts": 0,
            "Minimum": 967,
            "Peak": 967,
            "PrMode": "dyn",
            "PunCap": false,
            "Time": "2025-07-16T23:12:22Z",
            "UnachCap": false
        },
        {
            "AmbTemp": 16,
            "Average": 968,
            "Cap": 0,
            "CpuAvgFreq": 0,
            "CpuCapLim": 0,
            "CpuMax": 0,
            "CpuPwrSavLim": 100,
            "CpuUtil": 0,
            "CpuWatts": 169,
            "DimmWatts": 36,
            "FanWatts": 46,
            "GpuWatts": 0,
            "Minimum": 968,
            "Peak": 968,
            "PrMode": "dyn",
            "PunCap": false,
            "Time": "2025-07-16T23:12:32Z",
            "UnachCap": false
        },
        {
            "AmbTemp": 16,
            "Average": 967,
            "Cap": 0,
            "CpuAvgFreq": 0,
            "CpuCapLim": 0,
            "CpuMax": 0,
            "CpuPwrSavLim": 100,
            "CpuUtil": 0,
            "CpuWatts": 166,
            "DimmWatts": 36,
            "FanWatts": 46,
            "GpuWatts": 0,
            "Minimum": 967,
            "Peak": 968,
            "PrMode": "dyn",
            "PunCap": false,
            "Time": "2025-07-16T23:12:43Z",
            "UnachCap": false
        },
        {
            "AmbTemp": 15,
            "Average": 967,
            "Cap": 0,
            "CpuAvgFreq": 0,
            "CpuCapLim": 0,
            "CpuMax": 0,
            "CpuPwrSavLim": 100,
            "CpuUtil": 0,
            "CpuWatts": 168,
            "DimmWatts": 36,
            "FanWatts": 46,
            "GpuWatts": 0,
            "Minimum": 967,
            "Peak": 967,
            "PrMode": "dyn",
            "PunCap": false,
            "Time": "2025-07-16T23:12:53Z",
            "UnachCap": false
        },
        {
            "AmbTemp": 15,
            "Average": 967,
            "Cap": 0,
            "CpuAvgFreq": 0,
            "CpuCapLim": 0,
            "CpuMax": 0,
            "CpuPwrSavLim": 100,
            "CpuUtil": 0,
            "CpuWatts": 164,
            "DimmWatts": 36,
            "FanWatts": 46,
            "GpuWatts": 0,
            "Minimum": 967,
            "Peak": 968,
            "PrMode": "dyn",
            "PunCap": false,
            "Time": "2025-07-16T23:13:03Z",
            "UnachCap": false
        },
        {
            "AmbTemp": 16,
            "Average": 968,
            "Cap": 0,
            "CpuAvgFreq": 0,
            "CpuCapLim": 0,
            "CpuMax": 0,
            "CpuPwrSavLim": 100,
            "CpuUtil": 0,
            "CpuWatts": 167,
            "DimmWatts": 36,
            "FanWatts": 46,
            "GpuWatts": 0,
            "Minimum": 968,
            "Peak": 969,
            "PrMode": "dyn",
            "PunCap": false,
            "Time": "2025-07-16T23:13:14Z",
            "UnachCap": false
        },
        {
            "AmbTemp": 15,
            "Average": 969,
            "Cap": 0,
            "CpuAvgFreq": 0,
            "CpuCapLim": 0,
            "CpuMax": 0,
            "CpuPwrSavLim": 100,
            "CpuUtil": 0,
            "CpuWatts": 164,
            "DimmWatts": 36,
            "FanWatts": 46,
            "GpuWatts": 0,
            "Minimum": 969,
            "Peak": 969,
            "PrMode": "dyn",
            "PunCap": false,
            "Time": "2025-07-16T23:13:24Z",
            "UnachCap": false
        },
        {
            "AmbTemp": 15,
            "Average": 966,
            "Cap": 0,
            "CpuAvgFreq": 0,
            "CpuCapLim": 0,
            "CpuMax": 0,
            "CpuPwrSavLim": 100,
            "CpuUtil": 0,
            "CpuWatts": 167,
            "DimmWatts": 36,
            "FanWatts": 46,
            "GpuWatts": 0,
            "Minimum": 966,
            "Peak": 969,
            "PrMode": "dyn",
            "PunCap": false,
            "Time": "2025-07-16T23:13:34Z",
            "UnachCap": false
        },
        {
            "AmbTemp": 15,
            "Average": 967,
            "Cap": 0,
            "CpuAvgFreq": 0,
            "CpuCapLim": 0,
            "CpuMax": 0,
            "CpuPwrSavLim": 100,
            "CpuUtil": 0,
            "CpuWatts": 167,
            "DimmWatts": 36,
            "FanWatts": 46,
            "GpuWatts": 0,
            "Minimum": 967,
            "Peak": 968,
            "PrMode": "dyn",
            "PunCap": false,
            "Time": "2025-07-16T23:13:46Z",
            "UnachCap": false
        },
        {
            "AmbTemp": 15,
            "Average": 966,
            "Cap": 0,
            "CpuAvgFreq": 0,
            "CpuCapLim": 0,
            "CpuMax": 0,
            "CpuPwrSavLim": 100,
            "CpuUtil": 0,
            "CpuWatts": 166,
            "DimmWatts": 36,
            "FanWatts": 46,
            "GpuWatts": 0,
            "Minimum": 966,
            "Peak": 968,
            "PrMode": "dyn",
            "PunCap": false,
            "Time": "2025-07-16T23:13:56Z",
            "UnachCap": false
        },
        {
            "AmbTemp": 15,
            "Average": 966,
            "Cap": 0,
            "CpuAvgFreq": 0,
            "CpuCapLim": 0,
            "CpuMax": 0,
            "CpuPwrSavLim": 100,
            "CpuUtil": 0,
            "CpuWatts": 165,
            "DimmWatts": 36,
            "FanWatts": 46,
            "GpuWatts": 0,
            "Minimum": 966,
            "Peak": 967,
            "PrMode": "dyn",
            "PunCap": false,
            "Time": "2025-07-16T23:14:06Z",
            "UnachCap": false
        },
        {
            "AmbTemp": 16,
            "Average": 967,
            "Cap": 0,
            "CpuAvgFreq": 0,
            "CpuCapLim": 0,
            "CpuMax": 0,
            "CpuPwrSavLim": 100,
            "CpuUtil": 0,
            "CpuWatts": 166,
            "DimmWatts": 36,
            "FanWatts": 46,
            "GpuWatts": 0,
            "Minimum": 967,
            "Peak": 968,
            "PrMode": "dyn",
            "PunCap": false,
            "Time": "2025-07-16T23:14:17Z",
            "UnachCap": false
        },
        {
            "AmbTemp": 16,
            "Average": 967,
            "Cap": 0,
            "CpuAvgFreq": 0,
            "CpuCapLim": 0,
            "CpuMax": 0,
            "CpuPwrSavLim": 100,
            "CpuUtil": 0,
            "CpuWatts": 168,
            "DimmWatts": 36,
            "FanWatts": 46,
            "GpuWatts": 0,
            "Minimum": 967,
            "Peak": 968,
            "PrMode": "dyn",
            "PunCap": false,
            "Time": "2025-07-16T23:14:27Z",
            "UnachCap": false
        },
        {
            "AmbTemp": 16,
            "Average": 966,
            "Cap": 0,
            "CpuAvgFreq": 0,
            "CpuCapLim": 0,
            "CpuMax": 0,
            "CpuPwrSavLim": 100,
            "CpuUtil": 0,
            "CpuWatts": 167,
            "DimmWatts": 36,
            "FanWatts": 46,
            "GpuWatts": 0,
            "Minimum": 966,
            "Peak": 969,
            "PrMode": "dyn",
            "PunCap": false,
            "Time": "2025-07-16T23:14:37Z",
            "UnachCap": false
        },
        {
            "AmbTemp": 15,
            "Average": 967,
            "Cap": 0,
            "CpuAvgFreq": 0,
            "CpuCapLim": 0,
            "CpuMax": 0,
            "CpuPwrSavLim": 100,
            "CpuUtil": 0,
            "CpuWatts": 167,
            "DimmWatts": 36,
            "FanWatts": 46,
            "GpuWatts": 0,
            "Minimum": 967,
            "Peak": 967,
            "PrMode": "dyn",
            "PunCap": false,
            "Time": "2025-07-16T23:14:48Z",
            "UnachCap": false
        },
        {
            "AmbTemp": 15,
            "Average": 967,
            "Cap": 0,
            "CpuAvgFreq": 0,
            "CpuCapLim": 0,
            "CpuMax": 0,
            "CpuPwrSavLim": 100,
            "CpuUtil": 0,
            "CpuWatts": 168,
            "DimmWatts": 36,
            "FanWatts": 46,
            "GpuWatts": 0,
            "Minimum": 967,
            "Peak": 969,
            "PrMode": "dyn",
            "PunCap": false,
            "Time": "2025-07-16T23:14:58Z",
            "UnachCap": false
        },
        {
            "AmbTemp": 15,
            "Average": 968,
            "Cap": 0,
            "CpuAvgFreq": 0,
            "CpuCapLim": 0,
            "CpuMax": 0,
            "CpuPwrSavLim": 100,
            "CpuUtil": 0,
            "CpuWatts": 166,
            "DimmWatts": 36,
            "FanWatts": 46,
            "GpuWatts": 0,
            "Minimum": 968,
            "Peak": 968,
            "PrMode": "dyn",
            "PunCap": false,
            "Time": "2025-07-16T23:15:08Z",
            "UnachCap": false
        },
        {
            "AmbTemp": 15,
            "Average": 966,
            "Cap": 0,
            "CpuAvgFreq": 0,
            "CpuCapLim": 0,
            "CpuMax": 0,
            "CpuPwrSavLim": 100,
            "CpuUtil": 0,
            "CpuWatts": 162,
            "DimmWatts": 36,
            "FanWatts": 46,
            "GpuWatts": 0,
            "Minimum": 966,
            "Peak": 965,
            "PrMode": "dyn",
            "PunCap": false,
            "Time": "2025-07-16T23:15:19Z",
            "UnachCap": false
        },
        {
            "AmbTemp": 15,
            "Average": 966,
            "Cap": 0,
            "CpuAvgFreq": 0,
            "CpuCapLim": 0,
            "CpuMax": 0,
            "CpuPwrSavLim": 100,
            "CpuUtil": 0,
            "CpuWatts": 170,
            "DimmWatts": 36,
            "FanWatts": 46,
            "GpuWatts": 0,
            "Minimum": 966,
            "Peak": 968,
            "PrMode": "dyn",
            "PunCap": false,
            "Time": "2025-07-16T23:15:29Z",
            "UnachCap": false
        },
        {
            "AmbTemp": 15,
            "Average": 967,
            "Cap": 0,
            "CpuAvgFreq": 0,
            "CpuCapLim": 0,
            "CpuMax": 0,
            "CpuPwrSavLim": 100,
            "CpuUtil": 0,
            "CpuWatts": 169,
            "DimmWatts": 36,
            "FanWatts": 46,
            "GpuWatts": 0,
            "Minimum": 967,
            "Peak": 968,
            "PrMode": "dyn",
            "PunCap": false,
            "Time": "2025-07-16T23:15:39Z",
            "UnachCap": false
        },
        {
            "AmbTemp": 15,
            "Average": 968,
            "Cap": 0,
            "CpuAvgFreq": 0,
            "CpuCapLim": 0,
            "CpuMax": 0,
            "CpuPwrSavLim": 100,
            "CpuUtil": 0,
            "CpuWatts": 164,
            "DimmWatts": 36,
            "FanWatts": 46,
            "GpuWatts": 0,
            "Minimum": 968,
            "Peak": 968,
            "PrMode": "dyn",
            "PunCap": false,
            "Time": "2025-07-16T23:15:50Z",
            "UnachCap": false
        },
        {
            "AmbTemp": 15,
            "Average": 966,
            "Cap": 0,
            "CpuAvgFreq": 0,
            "CpuCapLim": 0,
            "CpuMax": 0,
            "CpuPwrSavLim": 100,
            "CpuUtil": 0,
            "CpuWatts": 166,
            "DimmWatts": 36,
            "FanWatts": 46,
            "GpuWatts": 0,
            "Minimum": 966,
            "Peak": 966,
            "PrMode": "dyn",
            "PunCap": false,
            "Time": "2025-07-16T23:16:00Z",
            "UnachCap": false
        },
        {
            "AmbTemp": 15,
            "Average": 967,
            "Cap": 0,
            "CpuAvgFreq": 0,
            "CpuCapLim": 0,
            "CpuMax": 0,
            "CpuPwrSavLim": 100,
            "CpuUtil": 0,
            "CpuWatts": 168,
            "DimmWatts": 36,
            "FanWatts": 46,
            "GpuWatts": 0,
            "Minimum": 967,
            "Peak": 969,
            "PrMode": "dyn",
            "PunCap": false,
            "Time": "2025-07-16T23:16:11Z",
            "UnachCap": false
        },
        {
            "AmbTemp": 16,
            "Average": 967,
            "Cap": 0,
            "CpuAvgFreq": 0,
            "CpuCapLim": 0,
            "CpuMax": 0,
            "CpuPwrSavLim": 100,
            "CpuUtil": 0,
            "CpuWatts": 167,
            "DimmWatts": 36,
            "FanWatts": 46,
            "GpuWatts": 0,
            "Minimum": 967,
            "Peak": 968,
            "PrMode": "dyn",
            "PunCap": false,
            "Time": "2025-07-16T23:16:21Z",
            "UnachCap": false
        },
        {
            "AmbTemp": 16,
            "Average": 967,
            "Cap": 0,
            "CpuAvgFreq": 0,
            "CpuCapLim": 0,
            "CpuMax": 0,
            "CpuPwrSavLim": 100,
            "CpuUtil": 0,
            "CpuWatts": 162,
            "DimmWatts": 36,
            "FanWatts": 46,
            "GpuWatts": 0,
            "Minimum": 967,
            "Peak": 969,
            "PrMode": "dyn",
            "PunCap": false,
            "Time": "2025-07-16T23:16:31Z",
            "UnachCap": false
        },
        {
            "AmbTemp": 15,
            "Average": 967,
            "Cap": 0,
            "CpuAvgFreq": 0,
            "CpuCapLim": 0,
            "CpuMax": 0,
            "CpuPwrSavLim": 100,
            "CpuUtil": 0,
            "CpuWatts": 164,
            "DimmWatts": 36,
            "FanWatts": 46,
            "GpuWatts": 0,
            "Minimum": 967,
            "Peak": 968,
            "PrMode": "dyn",
            "PunCap": false,
            "Time": "2025-07-16T23:16:42Z",
            "UnachCap": false
        },
        {
            "AmbTemp": 15,
            "Average": 968,
            "Cap": 0,
            "CpuAvgFreq": 0,
            "CpuCapLim": 0,
            "CpuMax": 0,
            "CpuPwrSavLim": 100,
            "CpuUtil": 0,
            "CpuWatts": 165,
            "DimmWatts": 36,
            "FanWatts": 46,
            "GpuWatts": 0,
            "Minimum": 968,
            "Peak": 970,
            "PrMode": "dyn",
            "PunCap": false,
            "Time": "2025-07-16T23:16:52Z",
            "UnachCap": false
        },
        {
            "AmbTemp": 16,
            "Average": 967,
            "Cap": 0,
            "CpuAvgFreq": 0,
            "CpuCapLim": 0,
            "CpuMax": 0,
            "CpuPwrSavLim": 100,
            "CpuUtil": 0,
            "CpuWatts": 170,
            "DimmWatts": 36,
            "FanWatts": 46,
            "GpuWatts": 0,
            "Minimum": 967,
            "Peak": 967,
            "PrMode": "dyn",
            "PunCap": false,
            "Time": "2025-07-16T23:17:03Z",
            "UnachCap": false
        },
        {
            "AmbTemp": 16,
            "Average": 967,
            "Cap": 0,
            "CpuAvgFreq": 0,
            "CpuCapLim": 0,
            "CpuMax": 0,
            "CpuPwrSavLim": 100,
            "CpuUtil": 0,
            "CpuWatts": 165,
            "DimmWatts": 36,
            "FanWatts": 46,
            "GpuWatts": 0,
            "Minimum": 967,
            "Peak": 968,
            "PrMode": "dyn",
            "PunCap": false,
            "Time": "2025-07-16T23:17:13Z",
            "UnachCap": false
        },
        {
            "AmbTemp": 15,
            "Average": 967,
            "Cap": 0,
            "CpuAvgFreq": 0,
            "CpuCapLim": 0,
            "CpuMax": 0,
            "CpuPwrSavLim": 100,
            "CpuUtil": 0,
            "CpuWatts": 167,
            "DimmWatts": 36,
            "FanWatts": 46,
            "GpuWatts": 0,
            "Minimum": 967,
            "Peak": 967,
            "PrMode": "dyn",
            "PunCap": false,
            "Time": "2025-07-16T23:17:23Z",
            "UnachCap": false
        },
        {
            "AmbTemp": 16,
            "Average": 967,
            "Cap": 0,
            "CpuAvgFreq": 0,
            "CpuCapLim": 0,
            "CpuMax": 0,
            "CpuPwrSavLim": 100,
            "CpuUtil": 0,
            "CpuWatts": 166,
            "DimmWatts": 36,
            "FanWatts": 46,
            "GpuWatts": 0,
            "Minimum": 967,
            "Peak": 966,
            "PrMode": "dyn",
            "PunCap": false,
            "Time": "2025-07-16T23:17:34Z",
            "UnachCap": false
        },
        {
            "AmbTemp": 15,
            "Average": 967,
            "Cap": 0,
            "CpuAvgFreq": 0,
            "CpuCapLim": 0,
            "CpuMax": 0,
            "CpuPwrSavLim": 100,
            "CpuUtil": 0,
            "CpuWatts": 164,
            "DimmWatts": 36,
            "FanWatts": 46,
            "GpuWatts": 0,
            "Minimum": 967,
            "Peak": 967,
            "PrMode": "dyn",
            "PunCap": false,
            "Time": "2025-07-16T23:17:44Z",
            "UnachCap": false
        },
        {
            "AmbTemp": 15,
            "Average": 967,
            "Cap": 0,
            "CpuAvgFreq": 0,
            "CpuCapLim": 0,
            "CpuMax": 0,
            "CpuPwrSavLim": 100,
            "CpuUtil": 0,
            "CpuWatts": 165,
            "DimmWatts": 36,
            "FanWatts": 46,
            "GpuWatts": 0,
            "Minimum": 967,
            "Peak": 968,
            "PrMode": "dyn",
            "PunCap": false,
            "Time": "2025-07-16T23:17:54Z",
            "UnachCap": false
        },
        {
            "AmbTemp": 15,
            "Average": 966,
            "Cap": 0,
            "CpuAvgFreq": 0,
            "CpuCapLim": 0,
            "CpuMax": 0,
            "CpuPwrSavLim": 100,
            "CpuUtil": 0,
            "CpuWatts": 167,
            "DimmWatts": 36,
            "FanWatts": 46,
            "GpuWatts": 0,
            "Minimum": 966,
            "Peak": 968,
            "PrMode": "dyn",
            "PunCap": false,
            "Time": "2025-07-16T23:18:05Z",
            "UnachCap": false
        },
        {
            "AmbTemp": 15,
            "Average": 966,
            "Cap": 0,
            "CpuAvgFreq": 0,
            "CpuCapLim": 0,
            "CpuMax": 0,
            "CpuPwrSavLim": 100,
            "CpuUtil": 0,
            "CpuWatts": 164,
            "DimmWatts": 36,
            "FanWatts": 46,
            "GpuWatts": 0,
            "Minimum": 966,
            "Peak": 969,
            "PrMode": "dyn",
            "PunCap": false,
            "Time": "2025-07-16T23:18:15Z",
            "UnachCap": false
        },
        {
            "AmbTemp": 15,
            "Average": 966,
            "Cap": 0,
            "CpuAvgFreq": 0,
            "CpuCapLim": 0,
            "CpuMax": 0,
            "CpuPwrSavLim": 100,
            "CpuUtil": 0,
            "CpuWatts": 164,
            "DimmWatts": 36,
            "FanWatts": 46,
            "GpuWatts": 0,
            "Minimum": 966,
            "Peak": 969,
            "PrMode": "dyn",
            "PunCap": false,
            "Time": "2025-07-16T23:18:26Z",
            "UnachCap": false
        },
        {
            "AmbTemp": 15,
            "Average": 966,
            "Cap": 0,
            "CpuAvgFreq": 0,
            "CpuCapLim": 0,
            "CpuMax": 0,
            "CpuPwrSavLim": 100,
            "CpuUtil": 0,
            "CpuWatts": 166,
            "DimmWatts": 36,
            "FanWatts": 46,
            "GpuWatts": 0,
            "Minimum": 966,
            "Peak": 969,
            "PrMode": "dyn",
            "PunCap": false,
            "Time": "2025-07-16T23:18:36Z",
            "UnachCap": false
        },
        {
            "AmbTemp": 15,
            "Average": 967,
            "Cap": 0,
            "CpuAvgFreq": 0,
            "CpuCapLim": 0,
            "CpuMax": 0,
            "CpuPwrSavLim": 100,
            "CpuUtil": 0,
            "CpuWatts": 165,
            "DimmWatts": 36,
            "FanWatts": 46,
            "GpuWatts": 0,
            "Minimum": 967,
            "Peak": 968,
            "PrMode": "dyn",
            "PunCap": false,
            "Time": "2025-07-16T23:18:46Z",
            "UnachCap": false
        },
        {
            "AmbTemp": 15,
            "Average": 967,
            "Cap": 0,
            "CpuAvgFreq": 0,
            "CpuCapLim": 0,
            "CpuMax": 0,
            "CpuPwrSavLim": 100,
            "CpuUtil": 0,
            "CpuWatts": 166,
            "DimmWatts": 36,
            "FanWatts": 46,
            "GpuWatts": 0,
            "Minimum": 967,
            "Peak": 968,
            "PrMode": "dyn",
            "PunCap": false,
            "Time": "2025-07-16T23:18:57Z",
            "UnachCap": false
        },
        {
            "AmbTemp": 15,
            "Average": 966,
            "Cap": 0,
            "CpuAvgFreq": 0,
            "CpuCapLim": 0,
            "CpuMax": 0,
            "CpuPwrSavLim": 100,
            "CpuUtil": 0,
            "CpuWatts": 167,
            "DimmWatts": 36,
            "FanWatts": 46,
            "GpuWatts": 0,
            "Minimum": 966,
            "Peak": 967,
            "PrMode": "dyn",
            "PunCap": false,
            "Time": "2025-07-16T23:19:07Z",
            "UnachCap": false
        },
        {
            "AmbTemp": 15,
            "Average": 967,
            "Cap": 0,
            "CpuAvgFreq": 0,
            "CpuCapLim": 0,
            "CpuMax": 0,
            "CpuPwrSavLim": 100,
            "CpuUtil": 0,
            "CpuWatts": 168,
            "DimmWatts": 36,
            "FanWatts": 46,
            "GpuWatts": 0,
            "Minimum": 967,
            "Peak": 968,
            "PrMode": "dyn",
            "PunCap": false,
            "Time": "2025-07-16T23:19:17Z",
            "UnachCap": false
        },
        {
            "AmbTemp": 15,
            "Average": 967,
            "Cap": 0,
            "CpuAvgFreq": 0,
            "CpuCapLim": 0,
            "CpuMax": 0,
            "CpuPwrSavLim": 100,
            "CpuUtil": 0,
            "CpuWatts": 167,
            "DimmWatts": 36,
            "FanWatts": 46,
            "GpuWatts": 0,
            "Minimum": 967,
            "Peak": 966,
            "PrMode": "dyn",
            "PunCap": false,
            "Time": "2025-07-16T23:19:28Z",
            "UnachCap": false
        },
        {
            "AmbTemp": 15,
            "Average": 967,
            "Cap": 0,
            "CpuAvgFreq": 0,
            "CpuCapLim": 0,
            "CpuMax": 0,
            "CpuPwrSavLim": 100,
            "CpuUtil": 0,
            "CpuWatts": 164,
            "DimmWatts": 36,
            "FanWatts": 46,
            "GpuWatts": 0,
            "Minimum": 967,
            "Peak": 967,
            "PrMode": "dyn",
            "PunCap": false,
            "Time": "2025-07-16T23:19:38Z",
            "UnachCap": false
        },
        {
            "AmbTemp": 15,
            "Average": 967,
            "Cap": 0,
            "CpuAvgFreq": 0,
            "CpuCapLim": 0,
            "CpuMax": 0,
            "CpuPwrSavLim": 100,
            "CpuUtil": 0,
            "CpuWatts": 164,
            "DimmWatts": 36,
            "FanWatts": 46,
            "GpuWatts": 0,
            "Minimum": 967,
            "Peak": 968,
            "PrMode": "dyn",
            "PunCap": false,
            "Time": "2025-07-16T23:19:48Z",
            "UnachCap": false
        },
        {
            "AmbTemp": 15,
            "Average": 966,
            "Cap": 0,
            "CpuAvgFreq": 0,
            "CpuCapLim": 0,
            "CpuMax": 0,
            "CpuPwrSavLim": 100,
            "CpuUtil": 0,
            "CpuWatts": 165,
            "DimmWatts": 36,
            "FanWatts": 46,
            "GpuWatts": 0,
            "Minimum": 966,
            "Peak": 967,
            "PrMode": "dyn",
            "PunCap": false,
            "Time": "2025-07-16T23:19:59Z",
            "UnachCap": false
        },
        {
            "AmbTemp": 15,
            "Average": 967,
            "Cap": 0,
            "CpuAvgFreq": 0,
            "CpuCapLim": 0,
            "CpuMax": 0,
            "CpuPwrSavLim": 100,
            "CpuUtil": 0,
            "CpuWatts": 170,
            "DimmWatts": 36,
            "FanWatts": 46,
            "GpuWatts": 0,
            "Minimum": 967,
            "Peak": 969,
            "PrMode": "dyn",
            "PunCap": false,
            "Time": "2025-07-16T23:20:09Z",
            "UnachCap": false
        },
        {
            "AmbTemp": 15,
            "Average": 967,
            "Cap": 0,
            "CpuAvgFreq": 0,
            "CpuCapLim": 0,
            "CpuMax": 0,
            "CpuPwrSavLim": 100,
            "CpuUtil": 0,
            "CpuWatts": 165,
            "DimmWatts": 36,
            "FanWatts": 46,
            "GpuWatts": 0,
            "Minimum": 967,
            "Peak": 967,
            "PrMode": "dyn",
            "PunCap": false,
            "Time": "2025-07-16T23:20:19Z",
            "UnachCap": false
        },
        {
            "AmbTemp": 15,
            "Average": 968,
            "Cap": 0,
            "CpuAvgFreq": 0,
            "CpuCapLim": 0,
            "CpuMax": 0,
            "CpuPwrSavLim": 100,
            "CpuUtil": 0,
            "CpuWatts": 166,
            "DimmWatts": 36,
            "FanWatts": 46,
            "GpuWatts": 0,
            "Minimum": 968,
            "Peak": 969,
            "PrMode": "dyn",
            "PunCap": false,
            "Time": "2025-07-16T23:20:30Z",
            "UnachCap": false
        },
        {
            "AmbTemp": 16,
            "Average": 966,
            "Cap": 0,
            "CpuAvgFreq": 0,
            "CpuCapLim": 0,
            "CpuMax": 0,
            "CpuPwrSavLim": 100,
            "CpuUtil": 0,
            "CpuWatts": 170,
            "DimmWatts": 36,
            "FanWatts": 46,
            "GpuWatts": 0,
            "Minimum": 966,
            "Peak": 965,
            "PrMode": "dyn",
            "PunCap": false,
            "Time": "2025-07-16T23:20:40Z",
            "UnachCap": false
        },
        {
            "AmbTemp": 16,
            "Average": 966,
            "Cap": 0,
            "CpuAvgFreq": 0,
            "CpuCapLim": 0,
            "CpuMax": 0,
            "CpuPwrSavLim": 100,
            "CpuUtil": 0,
            "CpuWatts": 169,
            "DimmWatts": 36,
            "FanWatts": 46,
            "GpuWatts": 0,
            "Minimum": 966,
            "Peak": 968,
            "PrMode": "dyn",
            "PunCap": false,
            "Time": "2025-07-16T23:20:50Z",
            "UnachCap": false
        },
        {
            "AmbTemp": 16,
            "Average": 966,
            "Cap": 0,
            "CpuAvgFreq": 0,
            "CpuCapLim": 0,
            "CpuMax": 0,
            "CpuPwrSavLim": 100,
            "CpuUtil": 0,
            "CpuWatts": 165,
            "DimmWatts": 36,
            "FanWatts": 46,
            "GpuWatts": 0,
            "Minimum": 966,
            "Peak": 968,
            "PrMode": "dyn",
            "PunCap": false,
            "Time": "2025-07-16T23:21:01Z",
            "UnachCap": false
        },
        {
            "AmbTemp": 16,
            "Average": 966,
            "Cap": 0,
            "CpuAvgFreq": 0,
            "CpuCapLim": 0,
            "CpuMax": 0,
            "CpuPwrSavLim": 100,
            "CpuUtil": 0,
            "CpuWatts": 170,
            "DimmWatts": 36,
            "FanWatts": 46,
            "GpuWatts": 0,
            "Minimum": 966,
            "Peak": 967,
            "PrMode": "dyn",
            "PunCap": false,
            "Time": "2025-07-16T23:21:11Z",
            "UnachCap": false
        },
        {
            "AmbTemp": 16,
            "Average": 967,
            "Cap": 0,
            "CpuAvgFreq": 0,
            "CpuCapLim": 0,
            "CpuMax": 0,
            "CpuPwrSavLim": 100,
            "CpuUtil": 0,
            "CpuWatts": 165,
            "DimmWatts": 36,
            "FanWatts": 46,
            "GpuWatts": 0,
            "Minimum": 967,
            "Peak": 967,
            "PrMode": "dyn",
            "PunCap": false,
            "Time": "2025-07-16T23:21:22Z",
            "UnachCap": false
        },
        {
            "AmbTemp": 16,
            "Average": 967,
            "Cap": 0,
            "CpuAvgFreq": 0,
            "CpuCapLim": 0,
            "CpuMax": 0,
            "CpuPwrSavLim": 100,
            "CpuUtil": 0,
            "CpuWatts": 165,
            "DimmWatts": 36,
            "FanWatts": 46,
            "GpuWatts": 0,
            "Minimum": 967,
            "Peak": 967,
            "PrMode": "dyn",
            "PunCap": false,
            "Time": "2025-07-16T23:21:32Z",
            "UnachCap": false
        },
        {
            "AmbTemp": 16,
            "Average": 966,
            "Cap": 0,
            "CpuAvgFreq": 0,
            "CpuCapLim": 0,
            "CpuMax": 0,
            "CpuPwrSavLim": 100,
            "CpuUtil": 0,
            "CpuWatts": 167,
            "DimmWatts": 36,
            "FanWatts": 46,
            "GpuWatts": 0,
            "Minimum": 966,
            "Peak": 968,
            "PrMode": "dyn",
            "PunCap": false,
            "Time": "2025-07-16T23:21:43Z",
            "UnachCap": false
        },
        {
            "AmbTemp": 16,
            "Average": 966,
            "Cap": 0,
            "CpuAvgFreq": 0,
            "CpuCapLim": 0,
            "CpuMax": 0,
            "CpuPwrSavLim": 100,
            "CpuUtil": 0,
            "CpuWatts": 166,
            "DimmWatts": 36,
            "FanWatts": 46,
            "GpuWatts": 0,
            "Minimum": 966,
            "Peak": 968,
            "PrMode": "dyn",
            "PunCap": false,
            "Time": "2025-07-16T23:21:53Z",
            "UnachCap": false
        },
        {
            "AmbTemp": 16,
            "Average": 966,
            "Cap": 0,
            "CpuAvgFreq": 0,
            "CpuCapLim": 0,
            "CpuMax": 0,
            "CpuPwrSavLim": 100,
            "CpuUtil": 0,
            "CpuWatts": 172,
            "DimmWatts": 36,
            "FanWatts": 46,
            "GpuWatts": 0,
            "Minimum": 966,
            "Peak": 968,
            "PrMode": "dyn",
            "PunCap": false,
            "Time": "2025-07-16T23:22:04Z",
            "UnachCap": false
        },
        {
            "AmbTemp": 16,
            "Average": 966,
            "Cap": 0,
            "CpuAvgFreq": 0,
            "CpuCapLim": 0,
            "CpuMax": 0,
            "CpuPwrSavLim": 100,
            "CpuUtil": 0,
            "CpuWatts": 163,
            "DimmWatts": 36,
            "FanWatts": 46,
            "GpuWatts": 0,
            "Minimum": 966,
            "Peak": 965,
            "PrMode": "dyn",
            "PunCap": false,
            "Time": "2025-07-16T23:22:14Z",
            "UnachCap": false
        },
        {
            "AmbTemp": 16,
            "Average": 966,
            "Cap": 0,
            "CpuAvgFreq": 0,
            "CpuCapLim": 0,
            "CpuMax": 0,
            "CpuPwrSavLim": 100,
            "CpuUtil": 0,
            "CpuWatts": 166,
            "DimmWatts": 36,
            "FanWatts": 46,
            "GpuWatts": 0,
            "Minimum": 966,
            "Peak": 971,
            "PrMode": "dyn",
            "PunCap": false,
            "Time": "2025-07-16T23:22:25Z",
            "UnachCap": false
        },
        {
            "AmbTemp": 16,
            "Average": 966,
            "Cap": 0,
            "CpuAvgFreq": 0,
            "CpuCapLim": 0,
            "CpuMax": 0,
            "CpuPwrSavLim": 100,
            "CpuUtil": 0,
            "CpuWatts": 166,
            "DimmWatts": 36,
            "FanWatts": 46,
            "GpuWatts": 0,
            "Minimum": 966,
            "Peak": 969,
            "PrMode": "dyn",
            "PunCap": false,
            "Time": "2025-07-16T23:22:35Z",
            "UnachCap": false
        },
        {
            "AmbTemp": 16,
            "Average": 966,
            "Cap": 0,
            "CpuAvgFreq": 0,
            "CpuCapLim": 0,
            "CpuMax": 0,
            "CpuPwrSavLim": 100,
            "CpuUtil": 0,
            "CpuWatts": 165,
            "DimmWatts": 36,
            "FanWatts": 46,
            "GpuWatts": 0,
            "Minimum": 966,
            "Peak": 969,
            "PrMode": "dyn",
            "PunCap": false,
            "Time": "2025-07-16T23:22:45Z",
            "UnachCap": false
        },
        {
            "AmbTemp": 16,
            "Average": 967,
            "Cap": 0,
            "CpuAvgFreq": 0,
            "CpuCapLim": 0,
            "CpuMax": 0,
            "CpuPwrSavLim": 100,
            "CpuUtil": 0,
            "CpuWatts": 165,
            "DimmWatts": 36,
            "FanWatts": 46,
            "GpuWatts": 0,
            "Minimum": 967,
            "Peak": 968,
            "PrMode": "dyn",
            "PunCap": false,
            "Time": "2025-07-16T23:22:55Z",
            "UnachCap": false
        },
        {
            "AmbTemp": 16,
            "Average": 967,
            "Cap": 0,
            "CpuAvgFreq": 0,
            "CpuCapLim": 0,
            "CpuMax": 0,
            "CpuPwrSavLim": 100,
            "CpuUtil": 0,
            "CpuWatts": 164,
            "DimmWatts": 36,
            "FanWatts": 46,
            "GpuWatts": 0,
            "Minimum": 967,
            "Peak": 966,
            "PrMode": "dyn",
            "PunCap": false,
            "Time": "2025-07-16T23:23:06Z",
            "UnachCap": false
        },
        {
            "AmbTemp": 16,
            "Average": 968,
            "Cap": 0,
            "CpuAvgFreq": 0,
            "CpuCapLim": 0,
            "CpuMax": 0,
            "CpuPwrSavLim": 100,
            "CpuUtil": 0,
            "CpuWatts": 164,
            "DimmWatts": 36,
            "FanWatts": 46,
            "GpuWatts": 0,
            "Minimum": 968,
            "Peak": 968,
            "PrMode": "dyn",
            "PunCap": false,
            "Time": "2025-07-16T23:23:17Z",
            "UnachCap": false
        },
        {
            "AmbTemp": 16,
            "Average": 967,
            "Cap": 0,
            "CpuAvgFreq": 0,
            "CpuCapLim": 0,
            "CpuMax": 0,
            "CpuPwrSavLim": 100,
            "CpuUtil": 0,
            "CpuWatts": 165,
            "DimmWatts": 36,
            "FanWatts": 46,
            "GpuWatts": 0,
            "Minimum": 967,
            "Peak": 965,
            "PrMode": "dyn",
            "PunCap": false,
            "Time": "2025-07-16T23:23:27Z",
            "UnachCap": false
        },
        {
            "AmbTemp": 16,
            "Average": 966,
            "Cap": 0,
            "CpuAvgFreq": 0,
            "CpuCapLim": 0,
            "CpuMax": 0,
            "CpuPwrSavLim": 100,
            "CpuUtil": 0,
            "CpuWatts": 169,
            "DimmWatts": 36,
            "FanWatts": 46,
            "GpuWatts": 0,
            "Minimum": 966,
            "Peak": 968,
            "PrMode": "dyn",
            "PunCap": false,
            "Time": "2025-07-16T23:23:37Z",
            "UnachCap": false
        },
        {
            "AmbTemp": 16,
            "Average": 967,
            "Cap": 0,
            "CpuAvgFreq": 0,
            "CpuCapLim": 0,
            "CpuMax": 0,
            "CpuPwrSavLim": 100,
            "CpuUtil": 0,
            "CpuWatts": 170,
            "DimmWatts": 36,
            "FanWatts": 46,
            "GpuWatts": 0,
            "Minimum": 967,
            "Peak": 971,
            "PrMode": "dyn",
            "PunCap": false,
            "Time": "2025-07-16T23:23:47Z",
            "UnachCap": false
        },
        {
            "AmbTemp": 16,
            "Average": 967,
            "Cap": 0,
            "CpuAvgFreq": 0,
            "CpuCapLim": 0,
            "CpuMax": 0,
            "CpuPwrSavLim": 100,
            "CpuUtil": 0,
            "CpuWatts": 165,
            "DimmWatts": 36,
            "FanWatts": 46,
            "GpuWatts": 0,
            "Minimum": 967,
            "Peak": 966,
            "PrMode": "dyn",
            "PunCap": false,
            "Time": "2025-07-16T23:23:58Z",
            "UnachCap": false
        },
        {
            "AmbTemp": 16,
            "Average": 967,
            "Cap": 0,
            "CpuAvgFreq": 0,
            "CpuCapLim": 0,
            "CpuMax": 0,
            "CpuPwrSavLim": 100,
            "CpuUtil": 0,
            "CpuWatts": 169,
            "DimmWatts": 36,
            "FanWatts": 46,
            "GpuWatts": 0,
            "Minimum": 967,
            "Peak": 966,
            "PrMode": "dyn",
            "PunCap": false,
            "Time": "2025-07-16T23:24:09Z",
            "UnachCap": false
        },
        {
            "AmbTemp": 16,
            "Average": 968,
            "Cap": 0,
            "CpuAvgFreq": 0,
            "CpuCapLim": 0,
            "CpuMax": 0,
            "CpuPwrSavLim": 100,
            "CpuUtil": 0,
            "CpuWatts": 165,
            "DimmWatts": 36,
            "FanWatts": 46,
            "GpuWatts": 0,
            "Minimum": 968,
            "Peak": 967,
            "PrMode": "dyn",
            "PunCap": false,
            "Time": "2025-07-16T23:24:19Z",
            "UnachCap": false
        },
        {
            "AmbTemp": 16,
            "Average": 968,
            "Cap": 0,
            "CpuAvgFreq": 0,
            "CpuCapLim": 0,
            "CpuMax": 0,
            "CpuPwrSavLim": 100,
            "CpuUtil": 0,
            "CpuWatts": 169,
            "DimmWatts": 36,
            "FanWatts": 46,
            "GpuWatts": 0,
            "Minimum": 968,
            "Peak": 968,
            "PrMode": "dyn",
            "PunCap": false,
            "Time": "2025-07-16T23:24:29Z",
            "UnachCap": false
        },
        {
            "AmbTemp": 16,
            "Average": 966,
            "Cap": 0,
            "CpuAvgFreq": 0,
            "CpuCapLim": 0,
            "CpuMax": 0,
            "CpuPwrSavLim": 100,
            "CpuUtil": 0,
            "CpuWatts": 168,
            "DimmWatts": 36,
            "FanWatts": 46,
            "GpuWatts": 0,
            "Minimum": 966,
            "Peak": 967,
            "PrMode": "dyn",
            "PunCap": false,
            "Time": "2025-07-16T23:24:39Z",
            "UnachCap": false
        },
        {
            "AmbTemp": 16,
            "Average": 968,
            "Cap": 0,
            "CpuAvgFreq": 0,
            "CpuCapLim": 0,
            "CpuMax": 0,
            "CpuPwrSavLim": 100,
            "CpuUtil": 0,
            "CpuWatts": 167,
            "DimmWatts": 36,
            "FanWatts": 46,
            "GpuWatts": 0,
            "Minimum": 968,
            "Peak": 970,
            "PrMode": "dyn",
            "PunCap": false,
            "Time": "2025-07-16T23:24:50Z",
            "UnachCap": false
        },
        {
            "AmbTemp": 16,
            "Average": 967,
            "Cap": 0,
            "CpuAvgFreq": 0,
            "CpuCapLim": 0,
            "CpuMax": 0,
            "CpuPwrSavLim": 100,
            "CpuUtil": 0,
            "CpuWatts": 164,
            "DimmWatts": 36,
            "FanWatts": 46,
            "GpuWatts": 0,
            "Minimum": 967,
            "Peak": 968,
            "PrMode": "dyn",
            "PunCap": false,
            "Time": "2025-07-16T23:25:00Z",
            "UnachCap": false
        },
        {
            "AmbTemp": 16,
            "Average": 967,
            "Cap": 0,
            "CpuAvgFreq": 0,
            "CpuCapLim": 0,
            "CpuMax": 0,
            "CpuPwrSavLim": 100,
            "CpuUtil": 0,
            "CpuWatts": 167,
            "DimmWatts": 36,
            "FanWatts": 46,
            "GpuWatts": 0,
            "Minimum": 967,
            "Peak": 970,
            "PrMode": "dyn",
            "PunCap": false,
            "Time": "2025-07-16T23:25:11Z",
            "UnachCap": false
        },
        {
            "AmbTemp": 16,
            "Average": 967,
            "Cap": 0,
            "CpuAvgFreq": 0,
            "CpuCapLim": 0,
            "CpuMax": 0,
            "CpuPwrSavLim": 100,
            "CpuUtil": 0,
            "CpuWatts": 166,
            "DimmWatts": 36,
            "FanWatts": 46,
            "GpuWatts": 0,
            "Minimum": 967,
            "Peak": 968,
            "PrMode": "dyn",
            "PunCap": false,
            "Time": "2025-07-16T23:25:21Z",
            "UnachCap": false
        },
        {
            "AmbTemp": 16,
            "Average": 967,
            "Cap": 0,
            "CpuAvgFreq": 0,
            "CpuCapLim": 0,
            "CpuMax": 0,
            "CpuPwrSavLim": 100,
            "CpuUtil": 0,
            "CpuWatts": 167,
            "DimmWatts": 36,
            "FanWatts": 46,
            "GpuWatts": 0,
            "Minimum": 967,
            "Peak": 968,
            "PrMode": "dyn",
            "PunCap": false,
            "Time": "2025-07-16T23:25:31Z",
            "UnachCap": false
        },
        {
            "AmbTemp": 16,
            "Average": 967,
            "Cap": 0,
            "CpuAvgFreq": 0,
            "CpuCapLim": 0,
            "CpuMax": 0,
            "CpuPwrSavLim": 100,
            "CpuUtil": 0,
            "CpuWatts": 168,
            "DimmWatts": 36,
            "FanWatts": 46,
            "GpuWatts": 0,
            "Minimum": 967,
            "Peak": 970,
            "PrMode": "dyn",
            "PunCap": false,
            "Time": "2025-07-16T23:25:42Z",
            "UnachCap": false
        },
        {
            "AmbTemp": 16,
            "Average": 967,
            "Cap": 0,
            "CpuAvgFreq": 0,
            "CpuCapLim": 0,
            "CpuMax": 0,
            "CpuPwrSavLim": 100,
            "CpuUtil": 0,
            "CpuWatts": 165,
            "DimmWatts": 36,
            "FanWatts": 46,
            "GpuWatts": 0,
            "Minimum": 967,
            "Peak": 969,
            "PrMode": "dyn",
            "PunCap": false,
            "Time": "2025-07-16T23:25:52Z",
            "UnachCap": false
        },
        {
            "AmbTemp": 16,
            "Average": 967,
            "Cap": 0,
            "CpuAvgFreq": 0,
            "CpuCapLim": 0,
            "CpuMax": 0,
            "CpuPwrSavLim": 100,
            "CpuUtil": 0,
            "CpuWatts": 165,
            "DimmWatts": 36,
            "FanWatts": 46,
            "GpuWatts": 0,
            "Minimum": 967,
            "Peak": 968,
            "PrMode": "dyn",
            "PunCap": false,
            "Time": "2025-07-16T23:26:03Z",
            "UnachCap": false
        },
        {
            "AmbTemp": 16,
            "Average": 966,
            "Cap": 0,
            "CpuAvgFreq": 0,
            "CpuCapLim": 0,
            "CpuMax": 0,
            "CpuPwrSavLim": 100,
            "CpuUtil": 0,
            "CpuWatts": 168,
            "DimmWatts": 36,
            "FanWatts": 46,
            "GpuWatts": 0,
            "Minimum": 966,
            "Peak": 968,
            "PrMode": "dyn",
            "PunCap": false,
            "Time": "2025-07-16T23:26:13Z",
            "UnachCap": false
        },
        {
            "AmbTemp": 16,
            "Average": 968,
            "Cap": 0,
            "CpuAvgFreq": 0,
            "CpuCapLim": 0,
            "CpuMax": 0,
            "CpuPwrSavLim": 100,
            "CpuUtil": 0,
            "CpuWatts": 166,
            "DimmWatts": 36,
            "FanWatts": 46,
            "GpuWatts": 0,
            "Minimum": 968,
            "Peak": 970,
            "PrMode": "dyn",
            "PunCap": false,
            "Time": "2025-07-16T23:26:24Z",
            "UnachCap": false
        },
        {
            "AmbTemp": 16,
            "Average": 967,
            "Cap": 0,
            "CpuAvgFreq": 0,
            "CpuCapLim": 0,
            "CpuMax": 0,
            "CpuPwrSavLim": 100,
            "CpuUtil": 0,
            "CpuWatts": 168,
            "DimmWatts": 36,
            "FanWatts": 46,
            "GpuWatts": 0,
            "Minimum": 967,
            "Peak": 967,
            "PrMode": "dyn",
            "PunCap": false,
            "Time": "2025-07-16T23:26:35Z",
            "UnachCap": false
        },
        {
            "AmbTemp": 16,
            "Average": 969,
            "Cap": 0,
            "CpuAvgFreq": 0,
            "CpuCapLim": 0,
            "CpuMax": 0,
            "CpuPwrSavLim": 100,
            "CpuUtil": 0,
            "CpuWatts": 163,
            "DimmWatts": 36,
            "FanWatts": 46,
            "GpuWatts": 0,
            "Minimum": 969,
            "Peak": 969,
            "PrMode": "dyn",
            "PunCap": false,
            "Time": "2025-07-16T23:26:45Z",
            "UnachCap": false
        },
        {
            "AmbTemp": 16,
            "Average": 968,
            "Cap": 0,
            "CpuAvgFreq": 0,
            "CpuCapLim": 0,
            "CpuMax": 0,
            "CpuPwrSavLim": 100,
            "CpuUtil": 0,
            "CpuWatts": 166,
            "DimmWatts": 36,
            "FanWatts": 46,
            "GpuWatts": 0,
            "Minimum": 968,
            "Peak": 970,
            "PrMode": "dyn",
            "PunCap": false,
            "Time": "2025-07-16T23:26:55Z",
            "UnachCap": false
        },
        {
            "AmbTemp": 16,
            "Average": 967,
            "Cap": 0,
            "CpuAvgFreq": 0,
            "CpuCapLim": 0,
            "CpuMax": 0,
            "CpuPwrSavLim": 100,
            "CpuUtil": 0,
            "CpuWatts": 164,
            "DimmWatts": 36,
            "FanWatts": 46,
            "GpuWatts": 0,
            "Minimum": 967,
            "Peak": 967,
            "PrMode": "dyn",
            "PunCap": false,
            "Time": "2025-07-16T23:27:06Z",
            "UnachCap": false
        },
        {
            "AmbTemp": 16,
            "Average": 968,
            "Cap": 0,
            "CpuAvgFreq": 0,
            "CpuCapLim": 0,
            "CpuMax": 0,
            "CpuPwrSavLim": 100,
            "CpuUtil": 0,
            "CpuWatts": 167,
            "DimmWatts": 36,
            "FanWatts": 46,
            "GpuWatts": 0,
            "Minimum": 968,
            "Peak": 967,
            "PrMode": "dyn",
            "PunCap": false,
            "Time": "2025-07-16T23:27:17Z",
            "UnachCap": false
        },
        {
            "AmbTemp": 16,
            "Average": 968,
            "Cap": 0,
            "CpuAvgFreq": 0,
            "CpuCapLim": 0,
            "CpuMax": 0,
            "CpuPwrSavLim": 100,
            "CpuUtil": 0,
            "CpuWatts": 166,
            "DimmWatts": 36,
            "FanWatts": 46,
            "GpuWatts": 0,
            "Minimum": 968,
            "Peak": 970,
            "PrMode": "dyn",
            "PunCap": false,
            "Time": "2025-07-16T23:27:27Z",
            "UnachCap": false
        },
        {
            "AmbTemp": 16,
            "Average": 968,
            "Cap": 0,
            "CpuAvgFreq": 0,
            "CpuCapLim": 0,
            "CpuMax": 0,
            "CpuPwrSavLim": 100,
            "CpuUtil": 0,
            "CpuWatts": 164,
            "DimmWatts": 36,
            "FanWatts": 46,
            "GpuWatts": 0,
            "Minimum": 968,
            "Peak": 965,
            "PrMode": "dyn",
            "PunCap": false,
            "Time": "2025-07-16T23:27:38Z",
            "UnachCap": false
        }
    ],
    "Samples": 120
}