{
    "@odata.context": "/redfish/v1/$metadata#Session.Session",
    "@odata.etag": "W/\"636BE69A\"",
    "@odata.id": "/redfish/v1/SessionService/Sessions/ctobmaas00000000689bd311a0d5c8c",
    "@odata.type": "#Session.v1_0_0.Session",
    "Id": "ctobmaas00000000689bd311a0d5c8c",
    "Description": "Manager User Session",
    "Name": "User Session",
    "Oem": {
        "Hpe": {
            "@odata.context": "/redfish/v1/$metadata#HpeiLOSession.HpeiLOSession",
            "@odata.type": "#HpeiLOSession.v2_1_0.HpeiLOSession",
            "AccessTime": "2025-08-13T00:36:45Z",
            "LoginTime": "2025-08-12T23:49:37Z",
            "MySession": false,
            "UserExpires": "2025-08-13T00:36:45Z",
            "UserIP": "172.22.245.2",
            "UserTag": "Remote Console",
            "UserType": "Local"
        }
    },
    "UserName": "Ctobmaas"
}