{
    "@odata.context": "/redfish/v1/$metadata#LogEntry.LogEntry",
    "@odata.etag": "W/\"25213012\"",
    "@odata.id": "/redfish/v1/Managers/1/LogServices/IEL/Entries/152",
    "@odata.type": "#LogEntry.v1_11_0.LogEntry",
    "Id": "152",
    "Created": "2025-06-13T00:29:36Z",
    "EntryType": "Oem",
    "Message": "On-board clock set; was (dd/mm/yyyy) 13/06/2025  00:29:36.",
    "MessageArgs": [],
    "MessageId": "35.10",
    "Name": "iLO Event Log",
    "Oem": {
        "Hpe": {
            "@odata.context": "/redfish/v1/$metadata#HpeLogEntry.HpeLogEntry",
            "@odata.type": "#HpeLogEntry.v2_4_0.HpeLogEntry",
            "Categories": [
                "Administration",
                "Configuration"
            ],
            "Class": 35,
            "ClassDescription": "iLO 7",
            "Code": 10,
            "Count": 1,
            "EventNumber": 1676,
            "Severity": "Informational",
            "Updated": "2025-06-13T00:29:36Z"
        }
    },
    "OemRecordFormat": "Hpe-iLOEventLog",
    "Severity": "OK"
}