{
    "@odata.context": "/redfish/v1/$metadata#LogEntry.LogEntry",
    "@odata.etag": "W/\"2791689033\"",
    "@odata.id": "/redfish/v1/Managers/1/LogServices/IEL/Entries/62",
    "@odata.type": "#LogEntry.v1_11_0.LogEntry",
    "Id": "62",
    "Created": "2025-06-11T15:59:55Z",
    "EntryType": "Oem",
    "Message": "Remote console session started by: Administrator - fe80::1afe:3108:facb:5cef(DNS name not found).",
    "MessageArgs": [],
    "MessageId": "35.1011",
    "Name": "iLO Event Log",
    "Oem": {
        "Hpe": {
            "@odata.context": "/redfish/v1/$metadata#HpeLogEntry.HpeLogEntry",
            "@odata.type": "#HpeLogEntry.v2_4_0.HpeLogEntry",
            "Categories": [
                "Security",
                "Administration"
            ],
            "Class": 35,
            "ClassDescription": "iLO 7",
            "Code": 1011,
            "Count": 1,
            "EventNumber": 1586,
            "Severity": "Informational",
            "Updated": "2025-06-11T15:59:55Z"
        }
    },
    "OemRecordFormat": "Hpe-iLOEventLog",
    "Severity": "OK"
}