{
    "@odata.context": "/redfish/v1/$metadata#LogEntry.LogEntry",
    "@odata.etag": "W/\"73C0C5B9\"",
    "@odata.id": "/redfish/v1/Systems/1/LogServices/Event/Entries/9",
    "@odata.type": "#LogEntry.v1_11_0.LogEntry",
    "Id": "9",
    "Created": "2001-01-13T04:10:06Z",
    "EntryType": "Oem",
    "EventId": "35d7b7e3-7831-a559-7a08-b05ae54dd13e",
    "EventTimestamp": "2001-01-13T04:10:06Z",
    "Links": {
        "OriginOfCondition": {
            "@odata.id": "/redfish/v1/Systems/1"
        }
    },
    "MessageId": "iLOEvents.3.16.ServerPostDiscoveryComplete",
    "Name": "Event",
    "OemRecordFormat": "Hpe-Event",
    "Severity": "OK"
}