{
    "@odata.context": "/redfish/v1/$metadata#NetworkDeviceFunction.NetworkDeviceFunction",
    "@odata.type": "#NetworkDeviceFunction.v1_9_0.NetworkDeviceFunction",
    "@odata.id": "/redfish/v1/Chassis/1/NetworkAdapters/DE07A000/NetworkDeviceFunctions/2",
    "@odata.etag": "W/\"A4C3E6F2\"",
    "Id": "2",
    "Name": "Network Device Function 2",
    "Status": {
        "Health": "OK",
        "State": "Enabled"
    },
    "Metrics": {
        "@odata.id": "/redfish/v1/Chassis/1/NetworkAdapters/DE07A000/NetworkDeviceFunctions/2/Metrics"
    },
    "NetDevFuncType": "Ethernet",
    "DeviceEnabled": true,
    "NetDevFuncCapabilities": [
        "Ethernet"
    ],
    "Ethernet": {
        "MACAddress": "84:16:0c:39:a1:e3",
        "PermanentMACAddress": "84:16:0c:39:a1:e3",
        "MTUSize": 1514,
        "MTUSizeMaximum": 9600
    },
    "BootMode": "PXE",
    "VirtualFunctionsEnabled": false,
    "MaxVirtualFunctions": 0,
    "AssignablePhysicalNetworkPorts": [
        {
            "@odata.id": "/redfish/v1/Chassis/1/NetworkAdapters/DE07A000/Ports/2"
        }
    ],
    "Links": {
        "PCIeFunction": {
            "@odata.id": "/redfish/v1/Chassis/1/PCIeDevices/DE07A000/PCIeFunctions/2"
        },
        "PhysicalNetworkPortAssignment": {
            "@odata.id": "/redfish/v1/Chassis/1/NetworkAdapters/DE07A000/Ports/2"
        }
    }
}